mlplay/__init__.py
mlplay/helloml.py
mlplay/test.py
mlplay/cv/__init__.py
mlplay/going_modular/__init__.py
mlplay/going_modular/demo.py
mlplay/going_modular/engine.py
mlplay/going_modular/helper_functions.py
mlplay/going_modular/model_builder.py
mlplay/going_modular/predictions.py
mlplay/going_modular/train.py
mlplay/going_modular/utils.py
mlplay-0.0.10.dist-info/LICENSE
mlplay-0.0.10.dist-info/METADATA
mlplay-0.0.10.dist-info/WHEEL
mlplay-0.0.10.dist-info/top_level.txt
mlplay-0.0.10.dist-info/RECORD
