Metadata-Version: 2.1
Name: mlplay
Version: 0.0.10
Summary: mlplay
Author: onemriganka
Keywords: ml,onemriganka,codes
Classifier: Development Status :: 1 - Planning
Classifier: Intended Audience :: Developers
Classifier: Programming Language :: Python :: 3
Classifier: Operating System :: Unix
Classifier: Operating System :: MacOS :: MacOS X
Classifier: Operating System :: Microsoft :: Windows
License-File: LICENSE
Requires-Dist: torch
Requires-Dist: matplotlib
Requires-Dist: torchvision
